{
  "title": "RSS",
  "icon": "",
  "id": "01FQC300GGWCA7A8H0SXY6P9FG",
  "description": "Mulighed for at vise et rss feed.",
  "resources": {
    "component": "https://raw.githubusercontent.com/os2display/display-templates/develop/build/rss.js?ts=1712322599255",
    "admin": "https://raw.githubusercontent.com/os2display/display-templates/develop/build/rss-admin.json?ts=1712322599255",
    "schema": "https://raw.githubusercontent.com/os2display/display-templates/develop/build/rss-schema.json?ts=1712322599255",
    "assets": [],
    "options": {},
    "content": {}
  }
}